mltoolkit_laht/__init__.py
mltoolkit_laht/data/BankReviews.csv
mltoolkit_laht/data_loading/__init__.py
mltoolkit_laht/data_loading/base_loader.py
mltoolkit_laht/data_loading/csv_loader.py
mltoolkit_laht/data_loading/excel_loader.py
mltoolkit_laht/data_loading/json_loader.py
mltoolkit_laht/data_loading/show_info_mixin.py
mltoolkit_laht/data_preprocessing/__init__.py
mltoolkit_laht/data_preprocessing/base_preprocessor.py
mltoolkit_laht/data_preprocessing/data_processing.py
mltoolkit_laht/data_visualization/__init__.py
mltoolkit_laht/data_visualization/base_visualizer.py
mltoolkit_laht/data_visualization/features_visualizer.py
mltoolkit_laht/evaluation/__init__.py
mltoolkit_laht/evaluation/base_evaluator.py
mltoolkit_laht/feature_engineering/__init__.py
mltoolkit_laht/feature_engineering/base_feature_engineer.py
mltoolkit_laht/modeling/__init__.py
mltoolkit_laht/modeling/base_trainer.py
mltoolkit_laht/utils/__init__.py
mltoolkit_laht/utils/logger.py
tests/__init__.py
tests/test_data_processing.py
tests/test_models.py
tests/test_utils.py
tests/test_visualization.py
mltoolkit_laht-0.2.2.dist-info/LICENSE
mltoolkit_laht-0.2.2.dist-info/METADATA
mltoolkit_laht-0.2.2.dist-info/WHEEL
mltoolkit_laht-0.2.2.dist-info/top_level.txt
mltoolkit_laht-0.2.2.dist-info/RECORD
