Metadata-Version: 2.1
Name: mltoolkit-laht
Version: 0.2.2
Summary: A data science and machine learning toolkit
Home-page: https://github.com/lehidalgo/mltoolkit-laht
Author: Leandro Alexis Hidalgo Torres
Author-email: le.hidalgot@gmail.com
License: UNKNOWN
Platform: UNKNOWN
Classifier: Programming Language :: Python :: 3
Classifier: License :: OSI Approved :: MIT License
Classifier: Operating System :: OS Independent
Requires-Python: >=3.9
License-File: LICENSE
Requires-Dist: numpy
Requires-Dist: pandas
Requires-Dist: scikit-learn
Requires-Dist: matplotlib
Requires-Dist: seaborn
